setup.py
helmer/__init__.py
helmer/helmer.py
helmer.egg-info/PKG-INFO
helmer.egg-info/SOURCES.txt
helmer.egg-info/dependency_links.txt
helmer.egg-info/entry_points.txt
helmer.egg-info/requires.txt
helmer.egg-info/top_level.txt