Metadata-Version: 1.0
Name: helmer
Version: 0.0.4
Summary: Very basic package manager for helm k8s package manager
Home-page: UNKNOWN
Author: Roman Dolgyi
Author-email: UNKNOWN
License: UNKNOWN
Platform: UNKNOWN
